macmod/__init__.py
macmod/macmod.py
modmac-0.1.0.dist-info/licenses/LICENCE
modmac-0.1.0.dist-info/METADATA
modmac-0.1.0.dist-info/WHEEL
modmac-0.1.0.dist-info/entry_points.txt
modmac-0.1.0.dist-info/top_level.txt
modmac-0.1.0.dist-info/RECORD
