Metadata-Version: 2.4
Name: modmac
Version: 0.1.0
Summary: A simple command-line tool to format MAC addresses in standard styles.
Home-page: https://github.com/Maksym-Ototiuk/macmod
Author: Maksym Ototiuk
Author-email: mac@masik.slmail.me
Classifier: Programming Language :: Python :: 3
Classifier: License :: OSI Approved :: Apache Software License
Classifier: Operating System :: OS Independent
Requires-Python: >=3.6
License-File: LICENCE
Requires-Dist: pyperclip
Dynamic: author
Dynamic: author-email
Dynamic: classifier
Dynamic: home-page
Dynamic: license-file
Dynamic: requires-dist
Dynamic: requires-python
Dynamic: summary
